webpage2telegraph
