Metadata-Version: 2.1
Name: webpage2telegraph
Version: 2021.6.14
Summary: Transfer webpage to Telegraph archive.
Home-page: https://github.com/NullPointerMaker/webpage2telegraph.adapter
Author: NullPointerMaker
License: UNKNOWN
Platform: UNKNOWN
Classifier: Programming Language :: Python :: 3
Classifier: License :: OSI Approved :: GNU General Public License v3 (GPLv3)
Classifier: Operating System :: OS Independent
Requires-Python: >=3.0
